{
  "id": "jm-aop-31-of-2013-the-defamation-act",
  "type": "statute",
  "title": "31 of 2013 - The Defamation Act",
  "title_en": "31 of 2013 - The Defamation Act",
  "short_name": "31 of 2013 - The Defamation Act",
  "status": "in_force",
  "url": "https://laws.moj.gov.jm/library/act-of-parliament/31-of-2013-the-defamation-act",
  "description": "Category: act_of_parliament | Source: https://laws.moj.gov.jm/library/act-of-parliament/31-of-2013-the-defamation-act | Year: 2013",
  "provisions": [],
  "definitions": []
}